consent_log/__init__.py
consent_log/apps.py
consent_log/models.py
consent_log/tests.py
consent_log/urls.py
consent_log/views.py
consent_log/management/commands/__init__.py
consent_log/management/commands/expireconsent.py
consent_log/migrations/0001_initial.py
consent_log/migrations/__init__.py
consent_log-0.1.dist-info/DESCRIPTION.rst
consent_log-0.1.dist-info/METADATA
consent_log-0.1.dist-info/RECORD
consent_log-0.1.dist-info/WHEEL
consent_log-0.1.dist-info/metadata.json
consent_log-0.1.dist-info/top_level.txt
