Metadata-Version: 2.0
Name: consent-log
Version: 0.1
Summary: Keeps a record of consents. Required by EU law
Home-page: http://github.com/rgammans/django-consent-log
Author: Gamma Science
Author-email: info@gammascience.co.uk
License: GPLv3
Platform: UNKNOWN
Classifier: License :: OSI Approved :: GNU General Public License v3 (GPLv3)
Classifier: Framework :: Django :: 2.0
Classifier: Framework :: Django :: 2.1
Classifier: Framework :: Django :: 2.2
Classifier: Framework :: Django :: 3.0
Classifier: Framework :: Django :: 3.1
Classifier: Programming Language :: Python :: 3
Classifier: Programming Language :: Python :: 3.7
Classifier: Programming Language :: Python :: 3.8
Classifier: Topic :: Internet :: WWW/HTTP
Classifier: Topic :: Internet :: WWW/HTTP :: Site Management
Requires: django
Requires-Dist: Django (>=2.0.0)
